ohmyadmin/__init__.py
ohmyadmin/actions/__init__.py
ohmyadmin/actions/actions.py
ohmyadmin/app.py
ohmyadmin/authentication/__init__.py
ohmyadmin/authentication/policy.py
ohmyadmin/breadcrumbs.py
ohmyadmin/colors.py
ohmyadmin/components/__init__.py
ohmyadmin/components/base.py
ohmyadmin/components/components.py
ohmyadmin/components/display.py
ohmyadmin/components/form.py
ohmyadmin/components/index.py
ohmyadmin/components/layout.py
ohmyadmin/components/menu.py
ohmyadmin/components/table.py
ohmyadmin/components/text.py
ohmyadmin/contracts.py
ohmyadmin/datasources/__init__.py
ohmyadmin/datasources/datasource.py
ohmyadmin/datasources/sqlalchemy.py
ohmyadmin/display_fields.py
ohmyadmin/filters.py
ohmyadmin/forms/__init__.py
ohmyadmin/forms/utils.py
ohmyadmin/helpers.py
ohmyadmin/htmx.py
ohmyadmin/menu.py
ohmyadmin/metrics/__init__.py
ohmyadmin/metrics/base.py
ohmyadmin/metrics/partition.py
ohmyadmin/metrics/progress.py
ohmyadmin/metrics/trend.py
ohmyadmin/metrics/value.py
ohmyadmin/middleware.py
ohmyadmin/ordering.py
ohmyadmin/pagination.py
ohmyadmin/py.typed
ohmyadmin/resources/__init__.py
ohmyadmin/resources/actions.py
ohmyadmin/resources/policy.py
ohmyadmin/resources/resource.py
ohmyadmin/routing.py
ohmyadmin/screens/__init__.py
ohmyadmin/screens/base.py
ohmyadmin/screens/display.py
ohmyadmin/screens/form.py
ohmyadmin/screens/index.py
ohmyadmin/screens/table.py
ohmyadmin/shortcuts.py
ohmyadmin/statics/favicon.png
ohmyadmin/statics/main.css
ohmyadmin/statics/main.js
ohmyadmin/statics/main.js.map
ohmyadmin/storages/__init__.py
ohmyadmin/storages/uploaders.py
ohmyadmin/templates/ohmyadmin/actions/callback.html
ohmyadmin/templates/ohmyadmin/actions/callback_menu.html
ohmyadmin/templates/ohmyadmin/actions/link.html
ohmyadmin/templates/ohmyadmin/actions/link_menu.html
ohmyadmin/templates/ohmyadmin/actions/modal.html
ohmyadmin/templates/ohmyadmin/actions/modal_menu.html
ohmyadmin/templates/ohmyadmin/actions/modal_modal.html
ohmyadmin/templates/ohmyadmin/actions/submit.html
ohmyadmin-0.5.5.dist-info/LICENSE
ohmyadmin-0.5.5.dist-info/METADATA
ohmyadmin-0.5.5.dist-info/WHEEL
ohmyadmin-0.5.5.dist-info/RECORD
