Metadata-Version: 2.1
Name: ohmyadmin
Version: 0.5.5
Summary: Awesome admin panel for your business.
Home-page: https://github.com/alex-oleshkevich/ohmyadmin
License: MIT
Author: Alex Oleshkevich
Author-email: alex.oleshkevich@gmail.com
Requires-Python: >=3.10,<4.0
Classifier: Development Status :: 5 - Production/Stable
Classifier: Environment :: Web Environment
Classifier: Intended Audience :: Developers
Classifier: License :: OSI Approved :: MIT License
Classifier: Operating System :: OS Independent
Classifier: Programming Language :: Python :: 3
Classifier: Programming Language :: Python :: 3.10
Classifier: Programming Language :: Python :: 3.11
Classifier: Programming Language :: Python :: 3.12
Classifier: Topic :: Software Development :: Libraries :: Python Modules
Classifier: Typing :: Typed
Requires-Dist: Jinja2 (>=3,<4)
Requires-Dist: WTForms (>=3,<4)
Requires-Dist: async-storages (>=0.5,<0.6)
Requires-Dist: python-multipart (>=0.0.9,<0.0.10)
Requires-Dist: python-slugify (>=8.0,<9.0)
Requires-Dist: starlette
Requires-Dist: starlette-babel
Requires-Dist: starlette-flash
Project-URL: Documentation, https://github.com/alex-oleshkevich/ohmyadmin
Project-URL: Repository, https://github.com/alex-oleshkevich/ohmyadmin
